ptmultiviews/__init__.py
ptmultiviews/_version.py
ptmultiviews/ptmultiviews.py
ptmultiviews-1.0.8.dist-info/licenses/LICENSE
ptmultiviews-1.0.8.dist-info/METADATA
ptmultiviews-1.0.8.dist-info/WHEEL
ptmultiviews-1.0.8.dist-info/entry_points.txt
ptmultiviews-1.0.8.dist-info/top_level.txt
ptmultiviews-1.0.8.dist-info/RECORD
